nb_tmpl_ctex/__init__.py
nb_tmpl_ctex-0.1.0.data/data/share/jupyter/nbconvert/templates/ctex/conf.json
nb_tmpl_ctex-0.1.0.data/data/share/jupyter/nbconvert/templates/ctex/index.tex.j2
nb_tmpl_ctex-0.1.0.data/data/share/jupyter/nbconvert/templates/ctex/report.tex.j2
nb_tmpl_ctex-0.1.0.dist-info/METADATA
nb_tmpl_ctex-0.1.0.dist-info/WHEEL
nb_tmpl_ctex-0.1.0.dist-info/licenses/LICENSE
nb_tmpl_ctex-0.1.0.dist-info/RECORD
